{
  "parent": "minecraft:recipes/root",
  "criteria": {
    "has_the_recipe": {
      "conditions": {
        "recipe": "prma:uzi_grip_cast"
      },
      "trigger": "minecraft:recipe_unlocked"
    },
    "has_uzi_grip_blueprint": {
      "conditions": {
        "items": [
          {
            "items": [
              "prma:uzi_grip_blueprint"
            ]
          }
        ]
      },
      "trigger": "minecraft:inventory_changed"
    }
  },
  "requirements": [
    [
      "has_uzi_grip_blueprint",
      "has_the_recipe"
    ]
  ],
  "rewards": {
    "recipes": [
      "prma:uzi_grip_cast"
    ]
  },
  "sends_telemetry_event": false
}